undu/__init__.py
undu-0.0.1.dist-info/METADATA
undu-0.0.1.dist-info/WHEEL
undu-0.0.1.dist-info/RECORD
