Metadata-Version: 2.4
Name: undu
Version: 0.0.1
Summary: Simple version control for humans. Full release coming soon.
Project-URL: Homepage, https://github.com/bdekraker/undu
Author-email: Benjamin DeKraker <aries.benjamin@gmail.com>
License: MIT
Keywords: backup,undo,vcs,version-control
Classifier: Development Status :: 1 - Planning
Classifier: License :: OSI Approved :: MIT License
Classifier: Programming Language :: Python :: 3
Requires-Python: >=3.8
